server/__init__.py
server/server.py
server/common/__init__.py
server/common/decos.py
server/common/descryptors.py
server/common/errors.py
server/common/metaclasses.py
server/common/utils.py
server/common/variables.py
server/docs/__init__.py
server/docs/source/__init__.py
server/docs/source/conf.py
server/logs/__init__.py
server/logs/config_client_log.py
server/logs/config_server_log.py
server/server/__init__.py
server/server/add_user.py
server/server/config_window.py
server/server/core.py
server/server/database.py
server/server/main_window.py
server/server/remove_user.py
server/server/stat_window.py
server/unit_tests/__init__.py
messenger_GB_server_acronics_31012023-1.dist-info/METADATA
messenger_GB_server_acronics_31012023-1.dist-info/WHEEL
messenger_GB_server_acronics_31012023-1.dist-info/top_level.txt
messenger_GB_server_acronics_31012023-1.dist-info/RECORD
