Metadata-Version: 2.1
Name: messenger-GB-server-acronics-31012023
Version: 1
Summary: Server package
Author: Michail Paramonov
Author-email: test@mail.ru
